{
    "home-manager": {
        "branch": "release-22.11",
        "description": "Manage a user environment using Nix",
        "homepage": "https://nix-community.github.io/home-manager/",
        "owner": "nix-community",
        "repo": "home-manager",
        "rev": "f9edbedaf015013eb35f8caacbe0c9666bbc16af",
        "sha256": "1cp2rpprcfl4mjsrsrpfg6278nf05a0mpl3m0snksvdalfmc5si5",
        "type": "tarball",
        "url": "https://github.com/nix-community/home-manager/archive/f9edbedaf015013eb35f8caacbe0c9666bbc16af.tar.gz",
        "url_template": "https://github.com/<owner>/<repo>/archive/<rev>.tar.gz"
    },
    "nix-thunk": {
        "branch": "v0.5.0.0",
        "description": null,
        "homepage": null,
        "owner": "obsidiansystems",
        "repo": "nix-thunk",
        "rev": "d32f4c1b91b24adc05a41d7dd8848a4f1dbd9c0a",
        "sha256": "0zpx9pkgf77k11anhwb49l7734yn0ipl6fvsrva85g9bbjqa1fhz",
        "type": "tarball",
        "url": "https://github.com/obsidiansystems/nix-thunk/archive/d32f4c1b91b24adc05a41d7dd8848a4f1dbd9c0a.tar.gz",
        "url_template": "https://github.com/<owner>/<repo>/archive/<rev>.tar.gz"
    },
    "nixos-22.11": {
        "branch": "nixos-22.11",
        "description": "Nix Packages collection",
        "homepage": "",
        "owner": "nixos",
        "repo": "nixpkgs",
        "rev": "d4a9ff82fc18723219b60c66fb2ccb0734c460eb",
        "sha256": "0ly23mqjzlygsnr0avji6ylyrl90rcqsmkcavg71kd60v8ydmw6c",
        "type": "tarball",
        "url": "https://github.com/nixos/nixpkgs/archive/d4a9ff82fc18723219b60c66fb2ccb0734c460eb.tar.gz",
        "url_template": "https://github.com/<owner>/<repo>/archive/<rev>.tar.gz"
    },
    "nixpkgs-unstable": {
        "branch": "nixpkgs-unstable",
        "description": "Nix Packages collection & NixOS",
        "homepage": "",
        "owner": "nixos",
        "repo": "nixpkgs",
        "rev": "31cd1b4afbaf0b1e81272ee9c31d1ab606503aed",
        "sha256": "1hd48vkdrj8rgihrkjfhr3amqlf3phjshqyylslb836n6vlp18pp",
        "type": "tarball",
        "url": "https://github.com/nixos/nixpkgs/archive/31cd1b4afbaf0b1e81272ee9c31d1ab606503aed.tar.gz",
        "url_template": "https://github.com/<owner>/<repo>/archive/<rev>.tar.gz"
    },
    "nur-combined": {
        "branch": "master",
        "description": "A repository of NUR that combines all repositories [maintainer=@Mic92] ",
        "homepage": "https://github.com/nix-community/NUR",
        "owner": "nix-community",
        "repo": "nur-combined",
        "rev": "970916eb704f4aea8af14ab8335cfb502b9b13f2",
        "sha256": "0mx08f7c788fvqgkfcw9lgzyrm38qiq3hj35lfmnz0dxd43hjmxg",
        "type": "tarball",
        "url": "https://github.com/nix-community/nur-combined/archive/970916eb704f4aea8af14ab8335cfb502b9b13f2.tar.gz",
        "url_template": "https://github.com/<owner>/<repo>/archive/<rev>.tar.gz"
    }
}
